ddht/__init__.py
ddht/_boot.py
ddht/_utils.py
ddht/abc.py
ddht/base_message.py
ddht/boot_info.py
ddht/cli_commands.py
ddht/cli_parser.py
ddht/constants.py
ddht/datagram.py
ddht/encryption.py
ddht/endpoint.py
ddht/enr.py
ddht/event.py
ddht/exceptions.py
ddht/handshake_schemes.py
ddht/kademlia.py
ddht/logging.py
ddht/main.py
ddht/message_registry.py
ddht/sedes.py
ddht/typing.py
ddht/upnp.py
ddht/validation.py
ddht/xdg.py
ddht/tools/__init__.py
ddht/tools/v5_strategies.py
ddht/tools/driver/__init__.py
ddht/tools/driver/_utils.py
ddht/tools/driver/abc.py
ddht/tools/driver/node.py
ddht/tools/driver/session.py
ddht/tools/driver/tester.py
ddht/tools/factories/__init__.py
ddht/tools/factories/boot_info.py
ddht/tools/factories/discovery.py
ddht/tools/factories/endpoint.py
ddht/tools/factories/kademlia.py
ddht/tools/factories/keys.py
ddht/tools/factories/node_id.py
ddht/tools/factories/socket.py
ddht/tools/factories/v5_1.py
ddht/v5/__init__.py
ddht/v5/abc.py
ddht/v5/app.py
ddht/v5/channel_services.py
ddht/v5/constants.py
ddht/v5/endpoint_tracker.py
ddht/v5/handshake.py
ddht/v5/message_dispatcher.py
ddht/v5/messages.py
ddht/v5/packer.py
ddht/v5/packets.py
ddht/v5/routing_table.py
ddht/v5/routing_table_manager.py
ddht/v5/tags.py
ddht/v5/topic_table.py
ddht/v5/typing.py
ddht/v5_1/__init__.py
ddht/v5_1/abc.py
ddht/v5_1/app.py
ddht/v5_1/client.py
ddht/v5_1/constants.py
ddht/v5_1/dispatcher.py
ddht/v5_1/envelope.py
ddht/v5_1/events.py
ddht/v5_1/exceptions.py
ddht/v5_1/messages.py
ddht/v5_1/network.py
ddht/v5_1/packets.py
ddht/v5_1/pool.py
ddht/v5_1/session.py
ddht-0.1.0a2.dist-info/LICENSE
ddht-0.1.0a2.dist-info/METADATA
ddht-0.1.0a2.dist-info/WHEEL
ddht-0.1.0a2.dist-info/entry_points.txt
ddht-0.1.0a2.dist-info/top_level.txt
ddht-0.1.0a2.dist-info/RECORD
