Metadata-Version: 2.1
Name: ddht
Version: 0.1.0a2
Summary: ddht: Implementation of the P2P Discoveryv5 Protocol
Home-page: https://github.com/ethereum/ddht
Author: The Ethereum Foundation
Author-email: snakecharmers@ethereum.org
License: MIT
Keywords: ethereum
Platform: UNKNOWN
Classifier: Development Status :: 3 - Alpha
Classifier: Intended Audience :: Developers
Classifier: License :: OSI Approved :: MIT License
Classifier: Natural Language :: English
Classifier: Programming Language :: Python :: 3
Classifier: Programming Language :: Python :: 3.8
Requires-Python: >=3.8, <4
Requires-Dist: async-service (<0.2,>=0.1.0a9)
Requires-Dist: cached-property (<2,>=1.5.1)
Requires-Dist: coincurve (<11.0.0,>=10.0.0)
Requires-Dist: cryptography (<3.2,>=3.0)
Requires-Dist: eth-enr (<0.4,>=0.3.0)
Requires-Dist: eth-hash[pycryptodome] (<1,>=0.1.4)
Requires-Dist: eth-keys (<0.4.0,>=0.3.3)
Requires-Dist: eth-typing (<3,>=2.2.2)
Requires-Dist: eth-utils (<2,>=1.8.4)
Requires-Dist: lru-dict (<2.0,>=1.1.6)
Requires-Dist: plyvel (<1.3,>=1.2.0)
Requires-Dist: py-evm (==0.3.0a19)
Requires-Dist: rlp (<3.0.0,>=2.0.0a1)
Requires-Dist: trio (<0.17,>=0.16.0)
Requires-Dist: trio-typing (<0.6,>=0.5.0)
Requires-Dist: upnp-port-forward (<0.2,>=0.1.1)
Provides-Extra: dev
Requires-Dist: bumpversion (<1,>=0.5.3) ; extra == 'dev'
Requires-Dist: pytest-watch (<5,>=4.1.0) ; extra == 'dev'
Requires-Dist: wheel ; extra == 'dev'
Requires-Dist: twine ; extra == 'dev'
Requires-Dist: ipython ; extra == 'dev'
Requires-Dist: factory-boy (==2.12.0) ; extra == 'dev'
Requires-Dist: hypothesis (<5,>=4.45.1) ; extra == 'dev'
Requires-Dist: pexpect (==4.8.0) ; extra == 'dev'
Requires-Dist: pytest (==6.0.1) ; extra == 'dev'
Requires-Dist: pytest-randomly (<3.2,>=3.1.0) ; extra == 'dev'
Requires-Dist: pytest-trio (<0.7,>=0.6.0) ; extra == 'dev'
Requires-Dist: pytest-xdist (==2.0.0) ; extra == 'dev'
Requires-Dist: tox (==3.19.0) ; extra == 'dev'
Requires-Dist: black (==19.10b0) ; extra == 'dev'
Requires-Dist: flake8 (==3.8.3) ; extra == 'dev'
Requires-Dist: isort (<6,>=5.1.4) ; extra == 'dev'
Requires-Dist: mypy (==0.782) ; extra == 'dev'
Requires-Dist: pydocstyle (<4,>=3.0.0) ; extra == 'dev'
Requires-Dist: Sphinx (<2,>=1.6.5) ; extra == 'dev'
Requires-Dist: sphinx-rtd-theme (>=0.1.9) ; extra == 'dev'
Requires-Dist: towncrier (<20,>=19.2.0) ; extra == 'dev'
Provides-Extra: doc
Requires-Dist: Sphinx (<2,>=1.6.5) ; extra == 'doc'
Requires-Dist: sphinx-rtd-theme (>=0.1.9) ; extra == 'doc'
Requires-Dist: towncrier (<20,>=19.2.0) ; extra == 'doc'
Provides-Extra: lint
Requires-Dist: black (==19.10b0) ; extra == 'lint'
Requires-Dist: flake8 (==3.8.3) ; extra == 'lint'
Requires-Dist: isort (<6,>=5.1.4) ; extra == 'lint'
Requires-Dist: mypy (==0.782) ; extra == 'lint'
Requires-Dist: pydocstyle (<4,>=3.0.0) ; extra == 'lint'
Provides-Extra: test
Requires-Dist: factory-boy (==2.12.0) ; extra == 'test'
Requires-Dist: hypothesis (<5,>=4.45.1) ; extra == 'test'
Requires-Dist: pexpect (==4.8.0) ; extra == 'test'
Requires-Dist: pytest (==6.0.1) ; extra == 'test'
Requires-Dist: pytest-randomly (<3.2,>=3.1.0) ; extra == 'test'
Requires-Dist: pytest-trio (<0.7,>=0.6.0) ; extra == 'test'
Requires-Dist: pytest-xdist (==2.0.0) ; extra == 'test'
Requires-Dist: tox (==3.19.0) ; extra == 'test'
